jointly_hic/__init__.py
jointly_hic/__main__.py
jointly_hic/entrypoint.py
jointly_hic/parser.py
jointly_hic/core/__init__.py
jointly_hic/core/config.py
jointly_hic/core/decomposer.py
jointly_hic/core/post_processor.py
jointly_hic/core/trajectory_analyzer.py
jointly_hic/hdf5db/__init__.py
jointly_hic/hdf5db/experiments2yaml.py
jointly_hic/hdf5db/hdf5db.py
jointly_hic/hdf5db/trackcsv2yaml.py
jointly_hic/methods/__init__.py
jointly_hic/methods/multivec.py
jointly_hic/methods/sparse_incremental_svd.py
jointly_hic/methods/trans_cooler_utils.py
jointly_hic/notebook_utils/__init__.py
jointly_hic/notebook_utils/bed9_conversion.py
jointly_hic/notebook_utils/bin_operations.py
jointly_hic/notebook_utils/encode_utils.py
jointly_hic/notebook_utils/heatmap.py
jointly_hic/notebook_utils/plotting.py
jointly_hic-1.0.5.dist-info/METADATA
jointly_hic-1.0.5.dist-info/WHEEL
jointly_hic-1.0.5.dist-info/entry_points.txt
jointly_hic-1.0.5.dist-info/licenses/LICENSE
jointly_hic-1.0.5.dist-info/RECORD
