Metadata-Version: 2.4
Name: jointly-hic
Version: 1.0.5
Summary: Genomics research toolkit for jointly embedding Hi-C 3D chromatin contact matrices into the same vector space
Author-email: Thomas Reimonn <thomas.reimonn@umassmed.edu>, Guoyun Chen <guoyun.chen5@umassmed.edu>, Nezar Abdennur <nezar.abdennur@umassmed.edu>, Hoang Tran <hoang.tran5@umassmed.edu>
License: GPL-3.0
License-File: LICENSE
Requires-Python: >=3.10
Requires-Dist: bioframe>=0.8.0
Requires-Dist: cooler>=0.10.3
Requires-Dist: cooltools>=0.7.1
Requires-Dist: cython>3.0.5
Requires-Dist: datashader>=0.17.0
Requires-Dist: leidenalg>=0.10.1
Requires-Dist: matplotlib>=3.6.0
Requires-Dist: numpy>=2.1
Requires-Dist: pandas>=2.1
Requires-Dist: pyarrow>=14
Requires-Dist: pybbi>=0.3.6
Requires-Dist: pydantic>=2.4.2
Requires-Dist: scikit-learn>=1.3.2
Requires-Dist: umap-learn[plot]>=0.5.4
Provides-Extra: dev
Requires-Dist: hatch>=1.10.0; extra == 'dev'
Requires-Dist: isort>=5.12.0; extra == 'dev'
Requires-Dist: pre-commit>=4.0.0; extra == 'dev'
Requires-Dist: pytest-cov>=4.1.0; extra == 'dev'
Requires-Dist: pytest-mock>=3.12.0; extra == 'dev'
Requires-Dist: pytest>=8.1.0; extra == 'dev'
Requires-Dist: ruff>=0.10.0; extra == 'dev'
Provides-Extra: notebook
Requires-Dist: black>=25.0; extra == 'notebook'
Requires-Dist: jupyter-black>=0.4.0; extra == 'notebook'
Requires-Dist: jupyter>=1.0.0; extra == 'notebook'
Requires-Dist: jupyterlab>=4.0.10; extra == 'notebook'
Requires-Dist: plotly>=5.18.0; extra == 'notebook'
